COPYING
MANIFEST.in
setup.py
petulant_bear.egg-info/PKG-INFO
petulant_bear.egg-info/SOURCES.txt
petulant_bear.egg-info/dependency_links.txt
petulant_bear.egg-info/requires.txt
petulant_bear.egg-info/top_level.txt
petulantbear/__init__.py
petulantbear/create_test_nc_file.py
petulantbear/netcdf2ncml.py
petulantbear/netcdf_etree.py