Metadata-Version: 1.1
Name: petulant-bear
Version: 0.1.3
Summary: Presents etree interface to netcdf4-python objects using NCML data model
Home-page: https://github.com/ioos/petulant-bear
Author: David Stuebe
Author-email: DStuebe@ASAScience.com
License: GPLv3
Keywords: netcdf lxml xml metadata ncml
Platform: UNKNOWN
Classifier: Development Status :: 3 - Alpha
Classifier: Intended Audience :: Developers
Classifier: Intended Audience :: Science/Research
Classifier: License :: OSI Approved :: GNU General Public License v3 (GPLv3)
Classifier: Operating System :: POSIX :: Linux
Classifier: Programming Language :: Python
Classifier: Topic :: Scientific/Engineering
